pandoc_recap.py
pandoc_recap-0.0.2.dist-info/LICENSE
pandoc_recap-0.0.2.dist-info/METADATA
pandoc_recap-0.0.2.dist-info/WHEEL
pandoc_recap-0.0.2.dist-info/entry_points.txt
pandoc_recap-0.0.2.dist-info/top_level.txt
pandoc_recap-0.0.2.dist-info/RECORD
