Metadata-Version: 2.1
Name: pandoc-recap
Version: 0.0.2
Summary: Render a recap of the notes (fenced divs) of the document
Author-email: Damien Clochard <damien.clochard@dalibo.com>
Project-URL: Homepage, https://github.com/daamien/pandoc-recap
Project-URL: Bug Tracker, https://github.com/daamien/pandoc-recap/issues
Classifier: Programming Language :: Python :: 3
Classifier: License :: OSI Approved :: MIT License
Classifier: Operating System :: OS Independent
Requires-Python: >=3.7
License-File: LICENSE
Requires-Dist: panflute
